src/regfile.sv
module regfile(
    input logic clk,
    input logic rst_n,

    input logic [4:0] address1,
    input logic [4:0] address2,
    output logic [31 : 0] read_data1,
    output logic [31 : 0] read_data2,

    // Write
    input logic [4:0] address3,
    input logic [31:0] write_data,
    input logic write_enable
);
    reg [31:0] registers [31:0];
    always @(posedge clk)begin
        
        if (rst_n == 1'b0) begin
            for (int i = 0; i < 32; i++) begin
                registers[i] <= 32'b0;
            end
        end
        else if (write_enable ==  1'b1 && address3 != 5'b0) begin
            registers[address3] <= write_data;
        end
    end
    always_comb begin
        read_data1 = registers[address1];
        read_data2 = registers[address2];
    end
endmodule

tb/regfile/dump.vcd
$version Generated by VerilatedVcd $end
$timescale 1ps $end
 $scope module  $end
  $var wire 1 # clk $end
  $var wire 1 $ rst_n $end
  $var wire 5 % address1 [4:0] $end
  $var wire 5 & address2 [4:0] $end
  $var wire 32 ' read_data1 [31:0] $end
  $var wire 32 ( read_data2 [31:0] $end
  $var wire 5 ) address3 [4:0] $end
  $var wire 32 * write_data [31:0] $end
  $var wire 1 + write_enable $end
  $scope module regfile $end
   $var wire 1 , clk $end
   $var wire 1 - rst_n $end
   $var wire 5 . address1 [4:0] $end
   $var wire 5 / address2 [4:0] $end
   $var wire 32 0 read_data1 [31:0] $end
   $var wire 32 1 read_data2 [31:0] $end
   $var wire 5 2 address3 [4:0] $end
   $var wire 32 3 write_data [31:0] $end
   $var wire 1 4 write_enable $end
   $var wire 32 5 registers[0] [31:0] $end
   $var wire 32 6 registers[1] [31:0] $end
   $var wire 32 7 registers[2] [31:0] $end
   $var wire 32 8 registers[3] [31:0] $end
   $var wire 32 9 registers[4] [31:0] $end
   $var wire 32 : registers[5] [31:0] $end
   $var wire 32 ; registers[6] [31:0] $end
   $var wire 32 < registers[7] [31:0] $end
   $var wire 32 = registers[8] [31:0] $end
   $var wire 32 > registers[9] [31:0] $end
   $var wire 32 ? registers[10] [31:0] $end
   $var wire 32 @ registers[11] [31:0] $end
   $var wire 32 A registers[12] [31:0] $end
   $var wire 32 B registers[13] [31:0] $end
   $var wire 32 C registers[14] [31:0] $end
   $var wire 32 D registers[15] [31:0] $end
   $var wire 32 E registers[16] [31:0] $end
   $var wire 32 F registers[17] [31:0] $end
   $var wire 32 G registers[18] [31:0] $end
   $var wire 32 H registers[19] [31:0] $end
   $var wire 32 I registers[20] [31:0] $end
   $var wire 32 J registers[21] [31:0] $end
   $var wire 32 K registers[22] [31:0] $end
   $var wire 32 L registers[23] [31:0] $end
   $var wire 32 M registers[24] [31:0] $end
   $var wire 32 N registers[25] [31:0] $end
   $var wire 32 O registers[26] [31:0] $end
   $var wire 32 P registers[27] [31:0] $end
   $var wire 32 Q registers[28] [31:0] $end
   $var wire 32 R registers[29] [31:0] $end
   $var wire 32 S registers[30] [31:0] $end
   $var wire 32 T registers[31] [31:0] $end
   $scope module unnamedblk1 $end
    $var wire 32 U i [31:0] $end
   $upscope $end
  $upscope $end
 $upscope $end
$enddefinitions $end


#0
1#
0$
b00000 %
b00000 &
b00000000000000000000000000000000 '
b00000000000000000000000000000000 (
b00000 )
b00000000000000000000000000000000 *
0+
1,
0-
b00000 .
b00000 /
b00000000000000000000000000000000 0
b00000000000000000000000000000000 1
b00000 2
b00000000000000000000000000000000 3
04
b00000000000000000000000000000000 5
b00000000000000000000000000000000 6
b00000000000000000000000000000000 7
b00000000000000000000000000000000 8
b00000000000000000000000000000000 9
b00000000000000000000000000000000 :
b00000000000000000000000000000000 ;
b00000000000000000000000000000000 <
b00000000000000000000000000000000 =
b00000000000000000000000000000000 >
b00000000000000000000000000000000 ?
b00000000000000000000000000000000 @
b00000000000000000000000000000000 A
b00000000000000000000000000000000 B
b00000000000000000000000000000000 C
b00000000000000000000000000000000 D
b00000000000000000000000000000000 E
b00000000000000000000000000000000 F
b00000000000000000000000000000000 G
b00000000000000000000000000000000 H
b00000000000000000000000000000000 I
b00000000000000000000000000000000 J
b00000000000000000000000000000000 K
b00000000000000000000000000000000 L
b00000000000000000000000000000000 M
b00000000000000000000000000000000 N
b00000000000000000000000000000000 O
b00000000000000000000000000000000 P
b00000000000000000000000000000000 Q
b00000000000000000000000000000000 R
b00000000000000000000000000000000 S
b00000000000000000000000000000000 T
b00000000000000000000000000100000 U
#5000
0#
0,
#10000
1#
1$
1,
1-
#15000
0#
0,
#20000
1#
1,
#21000
b10100 %
b11101 &
b10100 .
b11101 /
#22000
b01010 )
b00110011011100100100000001110000 *
1+
b01010 2
b00110011011100100100000001110000 3
14
#25000
0#
0,
#30000
1#
0+
1,
04
b00110011011100100100000001110000 ?
#31000
#32000
b10101 %
b11100 &
b10101 .
b11100 /
#33000
b11010 )
b11110101100111101110110000100001 *
1+
b11010 2
b11110101100111101110110000100001 3
14
#35000
0#
0,
#40000
1#
0+
1,
04
b11110101100111101110110000100001 O
#41000
#42000
b10111 %
b10000 &
b10111 .
b10000 /
#43000
b11100 )
b01011111010110000001011110000111 *
1+
b11100 2
b01011111010110000001011110000111 3
14
#45000
0#
0,
#50000
1#
0+
1,
04
b01011111010110000001011110000111 Q
#51000
#52000
b11101 %
b10001 &
b11101 .
b10001 /
#53000
b00111 )
b10100011110100010110010001000001 *
1+
b00111 2
b10100011110100010110010001000001 3
14
#55000
0#
0,
#60000
1#
0+
1,
04
b10100011110100010110010001000001 <
#61000
#62000
b00010 %
b01011 &
b00010 .
b01011 /
#63000
b11111 )
b11000001101100010001100110001111 *
1+
b11111 2
b11000001101100010001100110001111 3
14
#65000
0#
0,
#70000
1#
0+
1,
04
b11000001101100010001100110001111 T
#71000
#72000
b10011 %
b00011 &
b10011 .
b00011 /
#73000
b11110 )
b00100110011001011000101101101100 *
1+
b11110 2
b00100110011001011000101101101100 3
14
#75000
0#
0,
#80000
1#
0+
1,
04
b00100110011001011000101101101100 S
#81000
#82000
b00101 %
b11101 &
b00101 .
b11101 /
#83000
b01100 )
b11011001111011110110100110001000 *
1+
b01100 2
b11011001111011110110100110001000 3
14
#85000
0#
0,
#90000
1#
0+
1,
04
b11011001111011110110100110001000 A
#91000
#92000
b11110 %
b01111 &
b00100110011001011000101101101100 '
b11110 .
b01111 /
b00100110011001011000101101101100 0
#93000
b00001 )
b00010001111011011011011001101101 *
1+
b00001 2
b00010001111011011011011001101101 3
14
#95000
0#
0,
#100000
1#
0+
1,
04
b00010001111011011011011001101101 6
#101000
#102000
b11000 %
b11000 &
b00000000000000000000000000000000 '
b11000 .
b11000 /
b00000000000000000000000000000000 0
#103000
b10100 )
b00001001001010011010001101001001 *
1+
b10100 2
b00001001001010011010001101001001 3
14
#105000
0#
0,
#110000
1#
0+
1,
04
b00001001001010011010001101001001 I
#111000
#112000
b11001 %
b10011 &
b11001 .
b10011 /
#113000
b11110 )
b01010111100000010111010011110101 *
1+
b11110 2
b01010111100000010111010011110101 3
14
#115000
0#
0,
#120000
1#
0+
1,
04
b01010111100000010111010011110101 S
#121000
#122000
b10000 %
b00011 &
b10000 .
b00011 /
#123000
b11111 )
b01001100011101101101010110110001 *
1+
b11111 2
b01001100011101101101010110110001 3
14
#125000
0#
0,
#130000
1#
0+
1,
04
b01001100011101101101010110110001 T
#131000
#132000
b01001 %
b00001 &
b00010001111011011011011001101101 (
b01001 .
b00001 /
b00010001111011011011011001101101 1
#133000
b11000 )
b11011000100101110100110100111110 *
1+
b11000 2
b11011000100101110100110100111110 3
14
#135000
0#
0,
#140000
1#
0+
1,
04
b11011000100101110100110100111110 M
#141000
#142000
b11011 %
b01011 &
b00000000000000000000000000000000 (
b11011 .
b01011 /
b00000000000000000000000000000000 1
#143000
b01010 )
b10110000100010011100000101110001 *
1+
b01010 2
b10110000100010011100000101110001 3
14
#145000
0#
0,
#150000
1#
0+
1,
04
b10110000100010011100000101110001 ?
#151000
#152000
b00001 %
b10101 &
b00010001111011011011011001101101 '
b00001 .
b10101 /
b00010001111011011011011001101101 0
#153000
b10111 )
b11010100011110100000100111001111 *
1+
b10111 2
b11010100011110100000100111001111 3
14
#155000
0#
0,
#160000
1#
0+
1,
04
b11010100011110100000100111001111 L
#161000
#162000
b10001 %
b10100 &
b00000000000000000000000000000000 '
b00001001001010011010001101001001 (
b10001 .
b10100 /
b00000000000000000000000000000000 0
b00001001001010011010001101001001 1
#163000
b01101 )
b10101000100010010011110001100111 *
1+
b01101 2
b10101000100010010011110001100111 3
14
#165000
0#
0,
#170000
1#
0+
1,
04
b10101000100010010011110001100111 B
#171000
#172000
b10110 %
b10101 &
b00000000000000000000000000000000 (
b10110 .
b10101 /
b00000000000000000000000000000000 1
#173000
b11100 )
b11101001010001101001110011110000 *
1+
b11100 2
b11101001010001101001110011110000 3
14
#175000
0#
0,
#180000
1#
0+
1,
04
b11101001010001101001110011110000 Q
#181000
#182000
b01110 %
b11110 &
b01010111100000010111010011110101 (
b01110 .
b11110 /
b01010111100000010111010011110101 1
#183000
b01100 )
b10011100100110111111001001100001 *
1+
b01100 2
b10011100100110111111001001100001 3
14
#185000
0#
0,
#190000
1#
0+
1,
04
b10011100100110111111001001100001 A
#191000
#192000
b11000 %
b11011 &
b11011000100101110100110100111110 '
b00000000000000000000000000000000 (
b11000 .
b11011 /
b11011000100101110100110100111110 0
b00000000000000000000000000000000 1
#193000
b00010 )
b11000001011111111111101101001110 *
1+
b00010 2
b11000001011111111111101101001110 3
14
#195000
0#
0,
#200000
1#
0+
1,
04
b11000001011111111111101101001110 7
#201000
#202000
b01111 %
b01010 &
b00000000000000000000000000000000 '
b10110000100010011100000101110001 (
b01111 .
b01010 /
b00000000000000000000000000000000 0
b10110000100010011100000101110001 1
#203000
b01110 )
b00010100000010100110001000100110 *
1+
b01110 2
b00010100000010100110001000100110 3
14
#205000
0#
0,
#210000
1#
0+
1,
04
b00010100000010100110001000100110 C
#211000
#212000
b10110 %
b00001 &
b00010001111011011011011001101101 (
b10110 .
b00001 /
b00010001111011011011011001101101 1
#213000
b01001 )
b10001101010111000000100011110001 *
1+
b01001 2
b10001101010111000000100011110001 3
14
#215000
0#
0,
#220000
1#
0+
1,
04
b10001101010111000000100011110001 >
#221000
#222000
b01110 %
b10011 &
b00010100000010100110001000100110 '
b00000000000000000000000000000000 (
b01110 .
b10011 /
b00010100000010100110001000100110 0
b00000000000000000000000000000000 1
#223000
b00011 )
b00111011011001100101001011000100 *
1+
b00011 2
b00111011011001100101001011000100 3
14
#225000
0#
0,
#230000
1#
0+
1,
04
b00111011011001100101001011000100 8
#231000
#232000
b00110 %
b00010 &
b00000000000000000000000000000000 '
b11000001011111111111101101001110 (
b00110 .
b00010 /
b00000000000000000000000000000000 0
b11000001011111111111101101001110 1
#233000
b11110 )
b00000101010000111111001110111001 *
1+
b11110 2
b00000101010000111111001110111001 3
14
#235000
0#
0,
#240000
1#
0+
1,
04
b00000101010000111111001110111001 S
#241000
#242000
b11000 %
b01111 &
b11011000100101110100110100111110 '
b00000000000000000000000000000000 (
b11000 .
b01111 /
b11011000100101110100110100111110 0
b00000000000000000000000000000000 1
#243000
b01010 )
b00110010111001001110101111100111 *
1+
b01010 2
b00110010111001001110101111100111 3
14
#245000
0#
0,
#250000
1#
0+
1,
04
b00110010111001001110101111100111 ?
#251000
#252000
b11111 %
b01011 &
b01001100011101101101010110110001 '
b11111 .
b01011 /
b01001100011101101101010110110001 0
#253000
b10011 )
b01100001010001010011101111011001 *
1+
b10011 2
b01100001010001010011101111011001 3
14
#255000
0#
0,
#260000
1#
0+
1,
04
b01100001010001010011101111011001 H
#261000
#262000
b10001 %
b01000 &
b00000000000000000000000000000000 '
b10001 .
b01000 /
b00000000000000000000000000000000 0
#263000
b10101 )
b11110100011001000110010011001010 *
1+
b10101 2
b11110100011001000110010011001010 3
14
#265000
0#
0,
#270000
1#
0+
1,
04
b11110100011001000110010011001010 J
#271000
#272000
b10010 %
b11110 &
b00000101010000111111001110111001 (
b10010 .
b11110 /
b00000101010000111111001110111001 1
#273000
b10110 )
b10110101111111101101000001100010 *
1+
b10110 2
b10110101111111101101000001100010 3
14
#275000
0#
0,
#280000
1#
0+
1,
04
b10110101111111101101000001100010 K
#281000
#282000
b00101 %
b00001 &
b00010001111011011011011001101101 (
b00101 .
b00001 /
b00010001111011011011011001101101 1
#283000
b11001 )
b10111001100110001101010001111000 *
1+
b11001 2
b10111001100110001101010001111000 3
14
#285000
0#
0,
#290000
1#
0+
1,
04
b10111001100110001101010001111000 N
#291000
#292000
b00100 %
b11011 &
b00000000000000000000000000000000 (
b00100 .
b11011 /
b00000000000000000000000000000000 1
#293000
b01011 )
b00110001110011101010100000111011 *
1+
b01011 2
b00110001110011101010100000111011 3
14
#295000
0#
0,
#300000
1#
0+
1,
04
b00110001110011101010100000111011 @
#301000
#302000
b00111 %
b11111 &
b10100011110100010110010001000001 '
b01001100011101101101010110110001 (
b00111 .
b11111 /
b10100011110100010110010001000001 0
b01001100011101101101010110110001 1
#303000
b10101 )
b01001100000110011010011001000011 *
1+
b10101 2
b01001100000110011010011001000011 3
14
#305000
0#
0,
#310000
1#
0+
1,
04
b01001100000110011010011001000011 J
#311000
#312000
b00100 %
b10111 &
b00000000000000000000000000000000 '
b11010100011110100000100111001111 (
b00100 .
b10111 /
b00000000000000000000000000000000 0
b11010100011110100000100111001111 1
#313000
b00011 )
b11011110000010111110010010010111 *
1+
b00011 2
b11011110000010111110010010010111 3
14
#315000
0#
0,
#320000
1#
0+
1,
04
b11011110000010111110010010010111 8
#321000
#322000
b10101 %
b10101 &
b01001100000110011010011001000011 '
b01001100000110011010011001000011 (
b10101 .
b10101 /
b01001100000110011010011001000011 0
b01001100000110011010011001000011 1
#323000
b11001 )
b11011001110010111100011001110011 *
1+
b11001 2
b11011001110010111100011001110011 3
14
#325000
0#
0,
#330000
1#
0+
1,
04
b11011001110010111100011001110011 N
#331000
#332000
b10100 %
b01111 &
b00001001001010011010001101001001 '
b00000000000000000000000000000000 (
b10100 .
b01111 /
b00001001001010011010001101001001 0
b00000000000000000000000000000000 1
#333000
b10111 )
b01011101101000000001100110001010 *
1+
b10111 2
b01011101101000000001100110001010 3
14
#335000
0#
0,
#340000
1#
0+
1,
04
b01011101101000000001100110001010 L
#341000
#342000
b00111 %
b01010 &
b10100011110100010110010001000001 '
b00110010111001001110101111100111 (
b00111 .
b01010 /
b10100011110100010110010001000001 0
b00110010111001001110101111100111 1
#343000
b01111 )
b00110100001100010111001000110101 *
1+
b01111 2
b00110100001100010111001000110101 3
14
#345000
0#
0,
#350000
1#
0+
1,
04
b00110100001100010111001000110101 D
#351000
#352000
b00010 %
b10101 &
b11000001011111111111101101001110 '
b01001100000110011010011001000011 (
b00010 .
b10101 /
b11000001011111111111101101001110 0
b01001100000110011010011001000011 1
#353000
b11011 )
b11111000000010100100001111110110 *
1+
b11011 2
b11111000000010100100001111110110 3
14
#355000
0#
0,
#360000
1#
0+
1,
04
b11111000000010100100001111110110 P
#361000
#362000
b01101 %
b10010 &
b10101000100010010011110001100111 '
b00000000000000000000000000000000 (
b01101 .
b10010 /
b10101000100010010011110001100111 0
b00000000000000000000000000000000 1
#363000
b11010 )
b10110011101110110100100110101101 *
1+
b11010 2
b10110011101110110100100110101101 3
14
#365000
0#
0,
#370000
1#
0+
1,
04
b10110011101110110100100110101101 O
#371000
#372000
b00011 %
b10111 &
b11011110000010111110010010010111 '
b01011101101000000001100110001010 (
b00011 .
b10111 /
b11011110000010111110010010010111 0
b01011101101000000001100110001010 1
#373000
b01010 )
b11010100010010000001101011111001 *
1+
b01010 2
b11010100010010000001101011111001 3
14
#375000
0#
0,
#380000
1#
0+
1,
04
b11010100010010000001101011111001 ?
#381000
#382000
b11101 %
b11010 &
b00000000000000000000000000000000 '
b10110011101110110100100110101101 (
b11101 .
b11010 /
b00000000000000000000000000000000 0
b10110011101110110100100110101101 1
#383000
b01010011011100011010011110100111 *
1+
b01010011011100011010011110100111 3
14
#385000
0#
0,
#390000
1#
0+
1,
04
b01010011011100011010011110100111 ?
#391000
#392000
b01001 %
b01100 &
b10001101010111000000100011110001 '
b10011100100110111111001001100001 (
b01001 .
b01100 /
b10001101010111000000100011110001 0
b10011100100110111111001001100001 1
#393000
b11111 )
b10010100001101000100001100100001 *
1+
b11111 2
b10010100001101000100001100100001 3
14
#395000
0#
0,
#400000
1#
0+
1,
04
b10010100001101000100001100100001 T
#401000
#402000
b00110 %
b11001 &
b00000000000000000000000000000000 '
b11011001110010111100011001110011 (
b00110 .
b11001 /
b00000000000000000000000000000000 0
b11011001110010111100011001110011 1
#403000
b00010 )
b11011000101100001011001100101110 *
1+
b00010 2
b11011000101100001011001100101110 3
14
#405000
0#
0,
#410000
1#
0+
1,
04
b11011000101100001011001100101110 7
#411000
#412000
b01001 %
b11101 &
b10001101010111000000100011110001 '
b00000000000000000000000000000000 (
b01001 .
b11101 /
b10001101010111000000100011110001 0
b00000000000000000000000000000000 1
#413000
b01001 )
b00100101010100110111010010001001 *
1+
b01001 2
b00100101010100110111010010001001 3
14
#415000
0#
0,
#420000
1#
b00100101010100110111010010001001 '
0+
1,
b00100101010100110111010010001001 0
04
b00100101010100110111010010001001 >
#421000
#422000
b01000 %
b01011 &
b00000000000000000000000000000000 '
b00110001110011101010100000111011 (
b01000 .
b01011 /
b00000000000000000000000000000000 0
b00110001110011101010100000111011 1
#423000
b10011 )
b01001100111100010110111110100010 *
1+
b10011 2
b01001100111100010110111110100010 3
14
#425000
0#
0,
#430000
1#
0+
1,
04
b01001100111100010110111110100010 H
#431000
#432000
b10111 %
b11001 &
b01011101101000000001100110001010 '
b11011001110010111100011001110011 (
b10111 .
b11001 /
b01011101101000000001100110001010 0
b11011001110010111100011001110011 1
#433000
b11101 )
b11111011101010101010001101001110 *
1+
b11101 2
b11111011101010101010001101001110 3
14
#435000
0#
0,
#440000
1#
0+
1,
04
b11111011101010101010001101001110 R
#441000
#442000
b01100 %
b10110 &
b10011100100110111111001001100001 '
b10110101111111101101000001100010 (
b01100 .
b10110 /
b10011100100110111111001001100001 0
b10110101111111101101000001100010 1
#443000
b11111 )
b00111111000110101011100111011100 *
1+
b11111 2
b00111111000110101011100111011100 3
14
#445000
0#
0,
#450000
1#
0+
1,
04
b00111111000110101011100111011100 T
#451000
#452000
b00010 %
b10000 &
b11011000101100001011001100101110 '
b00000000000000000000000000000000 (
b00010 .
b10000 /
b11011000101100001011001100101110 0
b00000000000000000000000000000000 1
#453000
b01010 )
b11100110011111011001111110011010 *
1+
b01010 2
b11100110011111011001111110011010 3
14
#455000
0#
0,
#460000
1#
0+
1,
04
b11100110011111011001111110011010 ?
#461000
#462000
b00101 %
b11010 &
b00000000000000000000000000000000 '
b10110011101110110100100110101101 (
b00101 .
b11010 /
b00000000000000000000000000000000 0
b10110011101110110100100110101101 1
#463000
b10110 )
b11100111010010011010011000111000 *
1+
b10110 2
b11100111010010011010011000111000 3
14
#465000
0#
0,
#470000
1#
0+
1,
04
b11100111010010011010011000111000 K
#471000
#472000
b01010 %
b10010 &
b11100110011111011001111110011010 '
b00000000000000000000000000000000 (
b01010 .
b10010 /
b11100110011111011001111110011010 0
b00000000000000000000000000000000 1
#473000
b11010 )
b10010001011000000010111010011011 *
1+
b11010 2
b10010001011000000010111010011011 3
14
#475000
0#
0,
#480000
1#
0+
1,
04
b10010001011000000010111010011011 O
#481000
#482000
b10001 %
b01000 &
b00000000000000000000000000000000 '
b10001 .
b01000 /
b00000000000000000000000000000000 0
#483000
b00100 )
b00100101100001101000100101111001 *
1+
b00100 2
b00100101100001101000100101111001 3
14
#485000
0#
0,
#490000
1#
0+
1,
04
b00100101100001101000100101111001 9
#491000
#492000
b00110 %
b10101 &
b01001100000110011010011001000011 (
b00110 .
b10101 /
b01001100000110011010011001000011 1
#493000
b10011 )
b10010011101110010011101001100011 *
1+
b10011 2
b10010011101110010011101001100011 3
14
#495000
0#
0,
#500000
1#
0+
1,
04
b10010011101110010011101001100011 H
#501000
#502000
b00001 %
b10100 &
b00010001111011011011011001101101 '
b00001001001010011010001101001001 (
b00001 .
b10100 /
b00010001111011011011011001101101 0
b00001001001010011010001101001001 1
#503000
b11111 )
b01100000000100101110111011100011 *
1+
b11111 2
b01100000000100101110111011100011 3
14
#505000
0#
0,
#510000
1#
0+
1,
04
b01100000000100101110111011100011 T
#511000
#512000
b01001 %
b11110 &
b00100101010100110111010010001001 '
b00000101010000111111001110111001 (
b01001 .
b11110 /
b00100101010100110111010010001001 0
b00000101010000111111001110111001 1
#513000
b01011 )
b10110001101010001000011110010111 *
1+
b01011 2
b10110001101010001000011110010111 3
14
#515000
0#
0,
#520000
1#
0+
1,
04
b10110001101010001000011110010111 @
#521000
#522000
b10110 %
b10101 &
b11100111010010011010011000111000 '
b01001100000110011010011001000011 (
b10110 .
b10101 /
b11100111010010011010011000111000 0
b01001100000110011010011001000011 1
#523000
b11000010111100001100001011110111 *
1+
b11000010111100001100001011110111 3
14
#525000
0#
0,
#530000
1#
0+
1,
04
b11000010111100001100001011110111 @
#531000
#532000
b10100 %
b11011 &
b00001001001010011010001101001001 '
b11111000000010100100001111110110 (
b10100 .
b11011 /
b00001001001010011010001101001001 0
b11111000000010100100001111110110 1
#533000
b10010 )
b10111100000111001101010011011001 *
1+
b10010 2
b10111100000111001101010011011001 3
14
#535000
0#
0,
#540000
1#
0+
1,
04
b10111100000111001101010011011001 G
#541000
#542000
b10110 %
b10010 &
b11100111010010011010011000111000 '
b10111100000111001101010011011001 (
b10110 .
b10010 /
b11100111010010011010011000111000 0
b10111100000111001101010011011001 1
#543000
b00011 )
b10011110000010011111000001110001 *
1+
b00011 2
b10011110000010011111000001110001 3
14
#545000
0#
0,
#550000
1#
0+
1,
04
b10011110000010011111000001110001 8
#551000
#552000
b10000 %
b00011 &
b00000000000000000000000000000000 '
b10011110000010011111000001110001 (
b10000 .
b00011 /
b00000000000000000000000000000000 0
b10011110000010011111000001110001 1
#553000
b01111 )
b01010011010100010011100011000010 *
1+
b01111 2
b01010011010100010011100011000010 3
14
#555000
0#
0,
#560000
1#
0+
1,
04
b01010011010100010011100011000010 D
#561000
#562000
b10011 %
b10101 &
b10010011101110010011101001100011 '
b01001100000110011010011001000011 (
b10011 .
b10101 /
b10010011101110010011101001100011 0
b01001100000110011010011001000011 1
#563000
b10000 )
b11111100001001110000110000111001 *
1+
b10000 2
b11111100001001110000110000111001 3
14
#565000
0#
0,
#570000
1#
0+
1,
04
b11111100001001110000110000111001 E
#571000
#572000
b11000 %
b11110 &
b11011000100101110100110100111110 '
b00000101010000111111001110111001 (
b11000 .
b11110 /
b11011000100101110100110100111110 0
b00000101010000111111001110111001 1
#573000
b10100 )
b10110000011011101111111011110000 *
1+
b10100 2
b10110000011011101111111011110000 3
14
#575000
0#
0,
#580000
1#
0+
1,
04
b10110000011011101111111011110000 I
#581000
#582000
b10011 %
b00010 &
b10010011101110010011101001100011 '
b11011000101100001011001100101110 (
b10011 .
b00010 /
b10010011101110010011101001100011 0
b11011000101100001011001100101110 1
#583000
b01100 )
b10001111111110101111100001001110 *
1+
b01100 2
b10001111111110101111100001001110 3
14
#585000
0#
0,
#590000
1#
0+
1,
04
b10001111111110101111100001001110 A
#591000
#592000
b00101 %
b01111 &
b00000000000000000000000000000000 '
b01010011010100010011100011000010 (
b00101 .
b01111 /
b00000000000000000000000000000000 0
b01010011010100010011100011000010 1
#593000
b11010 )
b01000111110101000001011100010110 *
1+
b11010 2
b01000111110101000001011100010110 3
14
#595000
0#
0,
#600000
1#
0+
1,
04
b01000111110101000001011100010110 O
#601000
#602000
b11100 %
b00100 &
b11101001010001101001110011110000 '
b00100101100001101000100101111001 (
b11100 .
b00100 /
b11101001010001101001110011110000 0
b00100101100001101000100101111001 1
#603000
b11100 )
b11011100010101110100010011010010 *
1+
b11100 2
b11011100010101110100010011010010 3
14
#605000
0#
0,
#610000
1#
b11011100010101110100010011010010 '
0+
1,
b11011100010101110100010011010010 0
04
b11011100010101110100010011010010 Q
#611000
#612000
b00100 %
b01001 &
b00100101100001101000100101111001 '
b00100101010100110111010010001001 (
b00100 .
b01001 /
b00100101100001101000100101111001 0
b00100101010100110111010010001001 1
#613000
b00010 )
b11001101100010000100010100110010 *
1+
b00010 2
b11001101100010000100010100110010 3
14
#615000
0#
0,
#620000
1#
0+
1,
04
b11001101100010000100010100110010 7
#621000
#622000
b11110 %
b01011 &
b00000101010000111111001110111001 '
b11000010111100001100001011110111 (
b11110 .
b01011 /
b00000101010000111111001110111001 0
b11000010111100001100001011110111 1
#623000
b01000 )
b01011010001000111001000100010001 *
1+
b01000 2
b01011010001000111001000100010001 3
14
#625000
0#
0,
#630000
1#
0+
1,
04
b01011010001000111001000100010001 =
#631000
#632000
b11011 %
b00110 &
b11111000000010100100001111110110 '
b00000000000000000000000000000000 (
b11011 .
b00110 /
b11111000000010100100001111110110 0
b00000000000000000000000000000000 1
#633000
b01111 )
b11101011000001101111000100101000 *
1+
b01111 2
b11101011000001101111000100101000 3
14
#635000
0#
0,
#640000
1#
0+
1,
04
b11101011000001101111000100101000 D
#641000
#642000
b00100 %
b11111 &
b00100101100001101000100101111001 '
b01100000000100101110111011100011 (
b00100 .
b11111 /
b00100101100001101000100101111001 0
b01100000000100101110111011100011 1
#643000
b11000 )
b00011011110000111000000010101011 *
1+
b11000 2
b00011011110000111000000010101011 3
14
#645000
0#
0,
#650000
1#
0+
1,
04
b00011011110000111000000010101011 M
#651000
#652000
b01011 %
b00111 &
b11000010111100001100001011110111 '
b10100011110100010110010001000001 (
b01011 .
b00111 /
b11000010111100001100001011110111 0
b10100011110100010110010001000001 1
#653000
b10000 )
b00111111101001000000111000110110 *
1+
b10000 2
b00111111101001000000111000110110 3
14
#655000
0#
0,
#660000
1#
0+
1,
04
b00111111101001000000111000110110 E
#661000
#662000
b00111 %
b10010 &
b10100011110100010110010001000001 '
b10111100000111001101010011011001 (
b00111 .
b10010 /
b10100011110100010110010001000001 0
b10111100000111001101010011011001 1
#663000
b11110 )
b11100011000111011000010010111100 *
1+
b11110 2
b11100011000111011000010010111100 3
14
#665000
0#
0,
#670000
1#
0+
1,
04
b11100011000111011000010010111100 S
#671000
#672000
b10001 %
b00111 &
b00000000000000000000000000000000 '
b10100011110100010110010001000001 (
b10001 .
b00111 /
b00000000000000000000000000000000 0
b10100011110100010110010001000001 1
#673000
b11000 )
b11000110110011100100111000100111 *
1+
b11000 2
b11000110110011100100111000100111 3
14
#675000
0#
0,
#680000
1#
0+
1,
04
b11000110110011100100111000100111 M
#681000
#682000
b10100 %
b01010 &
b10110000011011101111111011110000 '
b11100110011111011001111110011010 (
b10100 .
b01010 /
b10110000011011101111111011110000 0
b11100110011111011001111110011010 1
#683000
b00111 )
b10000101101011101100100011110010 *
1+
b00111 2
b10000101101011101100100011110010 3
14
#685000
0#
0,
#690000
1#
0+
1,
04
b10000101101011101100100011110010 <
#691000
#692000
b10111 %
b01001 &
b01011101101000000001100110001010 '
b00100101010100110111010010001001 (
b10111 .
b01001 /
b01011101101000000001100110001010 0
b00100101010100110111010010001001 1
#693000
b01010 )
b01100001100101000001011110110010 *
1+
b01010 2
b01100001100101000001011110110010 3
14
#695000
0#
0,
#700000
1#
0+
1,
04
b01100001100101000001011110110010 ?
#701000
#702000
b11001 %
b00001 &
b11011001110010111100011001110011 '
b00010001111011011011011001101101 (
b11001 .
b00001 /
b11011001110010111100011001110011 0
b00010001111011011011011001101101 1
#703000
b10000 )
b11001001101001111110110011110001 *
1+
b10000 2
b11001001101001111110110011110001 3
14
#705000
0#
0,
#710000
1#
0+
1,
04
b11001001101001111110110011110001 E
#711000
#712000
b00010 %
b10010 &
b11001101100010000100010100110010 '
b10111100000111001101010011011001 (
b00010 .
b10010 /
b11001101100010000100010100110010 0
b10111100000111001101010011011001 1
#713000
b00001 )
b01100011100110000001101000010000 *
1+
b00001 2
b01100011100110000001101000010000 3
14
#715000
0#
0,
#720000
1#
0+
1,
04
b01100011100110000001101000010000 6
#721000
#722000
b11110 %
b10100 &
b11100011000111011000010010111100 '
b10110000011011101111111011110000 (
b11110 .
b10100 /
b11100011000111011000010010111100 0
b10110000011011101111111011110000 1
#723000
b10110 )
b01010001110011111011000011110011 *
1+
b10110 2
b01010001110011111011000011110011 3
14
#725000
0#
0,
#730000
1#
0+
1,
04
b01010001110011111011000011110011 K
#731000
#732000
b01010 %
b10110 &
b01100001100101000001011110110010 '
b01010001110011111011000011110011 (
b01010 .
b10110 /
b01100001100101000001011110110010 0
b01010001110011111011000011110011 1
#733000
b11101000101111010101000011000001 *
1+
b11101000101111010101000011000001 3
14
#735000
0#
0,
#740000
1#
b11101000101111010101000011000001 (
0+
1,
b11101000101111010101000011000001 1
04
b11101000101111010101000011000001 K
#741000
#742000
b00100 %
b00110 &
b00100101100001101000100101111001 '
b00000000000000000000000000000000 (
b00100 .
b00110 /
b00100101100001101000100101111001 0
b00000000000000000000000000000000 1
#743000
b11101 )
b10000001010110101111101000000011 *
1+
b11101 2
b10000001010110101111101000000011 3
14
#745000
0#
0,
#750000
1#
0+
1,
04
b10000001010110101111101000000011 R
#751000
#752000
b10110 %
b01110 &
b11101000101111010101000011000001 '
b00010100000010100110001000100110 (
b10110 .
b01110 /
b11101000101111010101000011000001 0
b00010100000010100110001000100110 1
#753000
b10110 )
b00111101111101011100001111110001 *
1+
b10110 2
b00111101111101011100001111110001 3
14
#755000
0#
0,
#760000
1#
b00111101111101011100001111110001 '
0+
1,
b00111101111101011100001111110001 0
04
b00111101111101011100001111110001 K
#761000
#762000
b11011 %
b10111 &
b11111000000010100100001111110110 '
b01011101101000000001100110001010 (
b11011 .
b10111 /
b11111000000010100100001111110110 0
b01011101101000000001100110001010 1
#763000
b11010 )
b10111010000111001101100011110111 *
1+
b11010 2
b10111010000111001101100011110111 3
14
#765000
0#
0,
